inertia/__init__.py
inertia/class_based_views.py
inertia/helpers.py
inertia/http.py
inertia/middleware.py
inertia/prop_classes.py
inertia/settings.py
inertia/share.py
inertia/templates/inertia.html
inertia/templates/inertia_ssr.html
inertia/test.py
inertia/tests/__init__.py
inertia/tests/settings.py
inertia/tests/test_encoder.py
inertia/tests/test_history.py
inertia/tests/test_middleware.py
inertia/tests/test_rendering.py
inertia/tests/test_settings.py
inertia/tests/test_ssr.py
inertia/tests/test_tests.py
inertia/tests/testapp/apps.py
inertia/tests/testapp/class_based_views.py
inertia/tests/testapp/layout.html
inertia/tests/testapp/models.py
inertia/tests/testapp/urls.py
inertia/tests/testapp/views.py
inertia/utils.py
inertia_django-1.1.0.dist-info/LICENSE
inertia_django-1.1.0.dist-info/METADATA
inertia_django-1.1.0.dist-info/WHEEL
inertia_django-1.1.0.dist-info/RECORD
