Metadata-Version: 2.1
Name: inertia-django
Version: 1.1.0
Summary: Django adapter for the InertiaJS framework
Home-page: https://github.com/inertiajs/inertia-django
License: MIT
Keywords: inertia,inertiajs,django
Author: Brandon Shar
Author-email: brandon@bellawatt.com
Requires-Python: >=3.8,<4.0
Classifier: Framework :: Django :: 4
Classifier: License :: OSI Approved :: MIT License
Classifier: Operating System :: OS Independent
Classifier: Programming Language :: Python :: 3
Classifier: Programming Language :: Python :: 3.8
Classifier: Programming Language :: Python :: 3.9
Classifier: Programming Language :: Python :: 3.10
Classifier: Programming Language :: Python :: 3.11
Classifier: Topic :: Software Development :: Libraries :: Python Modules
Requires-Dist: django (>=4)
Requires-Dist: requests (>=2,<3)
Project-URL: Repository, https://github.com/inertiajs/inertia-django
